coffee_roulette/__init__.py
coffee_roulette/create.py
coffee_roulette/get_pairs.py
coffee_roulette/modify.py
coffee_roulette/utils.py
coffee_roulette-0.4.6.dist-info/LICENSE.yaml
coffee_roulette-0.4.6.dist-info/METADATA
coffee_roulette-0.4.6.dist-info/WHEEL
coffee_roulette-0.4.6.dist-info/top_level.txt
coffee_roulette-0.4.6.dist-info/RECORD
