Metadata-Version: 2.1
Name: coffee-roulette
Version: 0.4.6
Summary: Pseudo-random pair generator
Author-email: Zane Mitrevica <zane.mitrevica@gmail.com>
License: BSD-3-Clause
Requires-Python: >=3.8.0
License-File: LICENSE.yaml
Requires-Dist: numpy
Requires-Dist: pandas
Requires-Dist: tabulate
Requires-Dist: types-tabulate
Requires-Dist: ruamel.yaml
Provides-Extra: dev
Requires-Dist: pytest ; extra == 'dev'
Requires-Dist: setuptools-scm ; extra == 'dev'
Requires-Dist: black ; extra == 'dev'
Requires-Dist: pre-commit ; extra == 'dev'
